[{"obj_id": 8, "annotations": {"tire_points": {"DF": [3744.21, 811.25], "PF": [-1, -1], "DR": [3803.8, 802.0], "PR": [-1, -1]}, "extremal_pairs": [[3743.87, 772.65, 3673.93, 769.25]], "non_extremal_pairs": [[3714.43, 797.82, 3671.59, 794.34], [3710.0, 785.47, 3680.73, 783.94]], "center_points": [[3693.9, 780.4], [3690.6, 791.1]], "has_mirror": 0}}, {"obj_id": 28, "annotations": {"tire_points": {"DF": [3909.66, 750.42], "PF": [-1, -1], "DR": [3975.91, 740.61], "PR": [-1, -1]}, "extremal_pairs": [[3905.74, 713.97, 3840.25, 710.4]], "non_extremal_pairs": [[3883.47, 735.49, 3841.48, 732.97], [3931.0, 685.83, 3882.54, 684.73], [3884.74, 717.95, 3847.26, 715.89]], "center_points": [[3860.77, 732.59], [3863.79, 720.51]], "has_mirror": 0}}, {"obj_id": 20, "annotations": {"tire_points": {"DF": [3419.81, 823.97], "PF": [-1, -1], "DR": [3486.3, 813.15], "PR": [-1, -1]}, "extremal_pairs": [[3409.3, 791.9, 3356.61, 786.42]], "non_extremal_pairs": [[3441.72, 765.78, 3402.02, 761.48], [3400.89, 810.32, 3349.99, 804.92], [3385.9, 800.6, 3357.91, 797.32], [3427.5, 781.5, 3380.9, 777.0], [3447.62, 778.48, 3380.32, 771.58]], "center_points": [[3367.59, 805.95], [3370.65, 796.9]], "has_mirror": 1}}, {"obj_id": 37, "annotations": {"tire_points": {"DF": [-1, -1], "PF": [2832.7, 1312.57], "DR": [-1, -1], "PR": [2591.05, 1380.51]}, "extremal_pairs": [[2406.15, 1218.1, 2510.34, 1271.97]], "non_extremal_pairs": [[2410.51, 1302.9, 2490.1, 1348.1], [2446.43, 1181.46, 2464.81, 1190.9]], "center_points": [[2454.58, 1186.36]], "has_mirror": 0}}]